addsub.vhdl
library ieee;
use ieee.std_logic_1164.all;

entity addsub is
port(
    A:          in std_logic_vector(3 downto 0);  -- 4-bit signed input A
    B:          in std_logic_vector(3 downto 0);  -- 4-bit signed input B
    sub:        in std_logic;                     -- 0: add, 1: subtract
    result:     out std_logic_vector(3 downto 0); -- 4-bit signed result
    overflow:   out std_logic                     -- overflow/underflow indicator
);
end addsub;

architecture rtl of addsub is
    signal B_complement : std_logic_vector(3 downto 0); -- B or its two's complement
    signal carry : std_logic_vector(3 downto 0);        -- carry bits
    signal sum : std_logic_vector(3 downto 0);          -- result
begin

    -- calculate two's complement of B if subtraction
    process(B, sub)
        variable inverted_B : std_logic_vector(3 downto 0);
    begin

        if sub = '1' then
            -- invert bits for two's complement
            for i in 0 to 3 loop
                inverted_B(i) := not B(i);
            end loop;
            
            -- add 1 to inverted_B
            if inverted_B(0) = '0' then
                B_complement(0) <= '1';
                B_complement(1) <= inverted_B(1);
                B_complement(2) <= inverted_B(2);
                B_complement(3) <= inverted_B(3);
            elsif inverted_B(1) = '0' then
                B_complement(0) <= '0';
                B_complement(1) <= '1';
                B_complement(2) <= inverted_B(2);
                B_complement(3) <= inverted_B(3);
            elsif inverted_B(2) = '0' then
                B_complement(0) <= '0';
                B_complement(1) <= '0';
                B_complement(2) <= '1';
                B_complement(3) <= inverted_B(3);
            elsif inverted_B(3) = '0' then
                B_complement(0) <= '0';
                B_complement(1) <= '0';
                B_complement(2) <= '0';
                B_complement(3) <= '1';
            else
                B_complement(0) <= '0';
                B_complement(1) <= '0';
                B_complement(2) <= '0';
                B_complement(3) <= '0';
            end if;
        else
            -- if addition, use B
            B_complement <= B;
        end if;
    end process;
    
    -- 4-bit adder with carry chain
    carry(0) <= '0'; -- initial carry
    
    -- generate sum and carry for each bit
    sum(0) <= A(0) xor B_complement(0) xor carry(0);
    carry(1) <= (A(0) and B_complement(0)) or (A(0) and carry(0)) or (B_complement(0) and carry(0));
    
    sum(1) <= A(1) xor B_complement(1) xor carry(1);
    carry(2) <= (A(1) and B_complement(1)) or (A(1) and carry(1)) or (B_complement(1) and carry(1));
    
    sum(2) <= A(2) xor B_complement(2) xor carry(2);
    carry(3) <= (A(2) and B_complement(2)) or (A(2) and carry(2)) or (B_complement(2) and carry(2));
    
    sum(3) <= A(3) xor B_complement(3) xor carry(3);
    
    -- connect sum to result
    result <= sum;
    
    -- detect overflow/underflow
    overflow <= (A(3) and B_complement(3) and not sum(3)) or (not A(3) and not B_complement(3) and sum(3));
    
end rtl;

addsub_tb.vhdl
library ieee;
use ieee.std_logic_1164.all;

entity addsub_tb is
end addsub_tb;

architecture behavioral of addsub_tb is
    -- component declaration for the adder/subtractor
    component addsub
    port(
        A:          in std_logic_vector(3 downto 0);  -- 4-bit signed input A
        B:          in std_logic_vector(3 downto 0);  -- 4-bit signed input B
        sub:        in std_logic;                     -- 0: add, 1: subtract
        result:     out std_logic_vector(3 downto 0); -- 4-bit signed result
        overflow:   out std_logic                     -- overflow/underflow indicator
    );
    end component;
    
    -- signals to connect to the adder/subtractor
    signal a_in: std_logic_vector(3 downto 0) := "0000";
    signal b_in: std_logic_vector(3 downto 0) := "0000";
    signal sub_mode: std_logic := '0';
    signal res: std_logic_vector(3 downto 0);
    signal ovf: std_logic;
begin

    -- instantiate the adder/subtractor
    addsub_inst: addsub
    port map (
        A => a_in,
        B => b_in,
        sub => sub_mode,
        result => res,
        overflow => ovf
    );
    
    -- process to stimulate adder/subtractor
    process
        -- procedure to test specific case
        procedure test_case(
            a_value: in std_logic_vector(3 downto 0);
            b_value: in std_logic_vector(3 downto 0);
            subtract: in std_logic
        ) is
        begin

            a_in <= a_value;
            b_in <= b_value;
            sub_mode <= subtract;
            wait for 10 ns;
        end procedure;
        
    begin
        
        -- simple addition with positive numbers
        test_case("0011", "0010", '0');  -- 3 + 2 = 5
        
        -- addition with negative number
        test_case("0101", "1110", '0');  -- 5 + (-2) = 3
        
        -- addition of two negative numbers
        test_case("1110", "1101", '0');  -- (-2) + (-3) = -5
        
        -- addition causing positive overflow
        test_case("0111", "0001", '0');  -- 7 + 1 = -8 (overflow)
        
        -- addition causing negative overflow
        test_case("1000", "1000", '0');  -- (-8) + (-8) = 0 (overflow)
        
        -- simple subtraction with positive numbers
        test_case("0110", "0011", '1');  -- 6 - 3 = 3
        
        -- subtraction resulting in negative number
        test_case("0010", "0011", '1');  -- 2 - 3 = -1
        
        -- subtraction of negative number
        test_case("0011", "1110", '1');  -- 3 - (-2) = 5
        
        -- subtraction causing positive overflow
        test_case("0111", "1000", '1');  -- 7 - (-8) = 15 -> -1 (overflow)
        
        -- subtraction causing negative overflow
        test_case("1000", "0001", '1');  -- (-8) - 1 = -9 -> 7 (overflow)
        
        assert false report "End of test" severity note;
        wait;
    end process;
    
end behavioral;

addsub.vcd
$date
  Tue Apr  1 19:47:59 2025
$end
$version
  GHDL v0
$end
$timescale
  1 fs
$end
$scope module standard $end
$upscope $end
$scope module std_logic_1164 $end
$upscope $end
$scope module addsub_tb $end
$var reg 4 ! a_in[3:0] $end
$var reg 4 " b_in[3:0] $end
$var reg 1 # sub_mode $end
$var reg 4 $ res[3:0] $end
$var reg 1 % ovf $end
$scope module addsub_inst $end
$var reg 4 & a[3:0] $end
$var reg 4 ' b[3:0] $end
$var reg 1 ( sub $end
$var reg 4 ) result[3:0] $end
$var reg 1 * overflow $end
$var reg 4 + b_complement[3:0] $end
$var reg 4 , carry[3:0] $end
$var reg 4 - sum[3:0] $end
$upscope $end
$upscope $end
$enddefinitions $end
#0
b0011 !
b0010 "
0#
b0101 $
0%
b0011 &
b0010 '
0(
b0101 )
0*
b0010 +
b0100 ,
b0101 -
#10000000
b0101 !
b1110 "
b0011 $
b0101 &
b1110 '
b0011 )
b1110 +
b1000 ,
b0011 -
#20000000
b1110 !
b1101 "
b1011 $
0%
b1110 &
b1101 '
b1011 )
0*
b1101 +
b1000 ,
b1011 -
#30000000
b0111 !
b0001 "
b1000 $
1%
b0111 &
b0001 '
b1000 )
1*
b0001 +
b1110 ,
b1000 -
#40000000
b1000 !
b1000 "
b0000 $
1%
b1000 &
b1000 '
b0000 )
1*
b1000 +
b0000 ,
b0000 -
#50000000
b0110 !
b0011 "
1#
b0011 $
0%
b0110 &
b0011 '
1(
b0011 )
0*
b1101 +
b1000 ,
b0011 -
#60000000
b0010 !
b1111 $
b0010 &
b1111 )
b0000 ,
b1111 -
#70000000
b0011 !
b1110 "
b0101 $
0%
b0011 &
b1110 '
b0101 )
0*
b0010 +
b0100 ,
b0101 -
#80000000
b0111 !
b1000 "
b1111 $
b0111 &
b1000 '
b1111 )
b1000 +
b0000 ,
b1111 -
#90000000
b1000 !
b0001 "
b0111 $
1%
b1000 &
b0001 '
b0111 )
1*
b1111 +
b0111 -
